SearchStrategyAnalysis/Pathfinder.py
SearchStrategyAnalysis/__init__.py
SearchStrategyAnalysis/appTrial.py
SearchStrategyAnalysis/heatmap.py
jsl_pathfinder-1.4.3.dist-info/LICENSE
jsl_pathfinder-1.4.3.dist-info/METADATA
jsl_pathfinder-1.4.3.dist-info/WHEEL
jsl_pathfinder-1.4.3.dist-info/entry_points.txt
jsl_pathfinder-1.4.3.dist-info/top_level.txt
jsl_pathfinder-1.4.3.dist-info/RECORD
