Metadata-Version: 2.1
Name: jsl-pathfinder
Version: 1.4.3
Summary: Morris Water Maze Search Strategy Analysis
Home-page: https://github.com/MatthewBCooke/Pathfinder
Author: Matthew Cooke
Author-email: matthew.cooke@ubc.ca
License: GNU
Keywords: morris water maze jason snyder lab search strategy strategies analysis
Platform: UNKNOWN
Classifier: Development Status :: 5 - Production/Stable
Classifier: Intended Audience :: Science/Research
Classifier: Natural Language :: English
Classifier: License :: OSI Approved :: GNU General Public License v3 or later (GPLv3+)
Classifier: Topic :: Scientific/Engineering :: Information Analysis
Classifier: Programming Language :: Python :: 3.5
Requires-Dist: xlrd (==1.2.0)
Requires-Dist: plotly
Requires-Dist: pillow
Requires-Dist: matplotlib
Requires-Dist: scipy
